pydiarization/config.py
pydiarization/diarization_wrapper.py
pydiarization/kaldi_mfcc.conf
pydiarization/run.py
pydiarization/test_diarization_wrapper.py
pydiarization-0.4.dist-info/METADATA
pydiarization-0.4.dist-info/WHEEL
pydiarization-0.4.dist-info/top_level.txt
pydiarization-0.4.dist-info/RECORD
