Metadata-Version: 2.1
Name: pydiarization
Version: 0.4
Summary: Diarization toolkit wrapper
Home-page: https://github.com/wdroz/IBDiarization/tree/master/src/pydiarization
Author: William Droz
Author-email: william.droz@idiap.ch
License: UNKNOWN
Platform: UNKNOWN
Classifier: Programming Language :: Python :: 3
Classifier: License :: OSI Approved :: GNU General Public License v3 (GPLv3)
Classifier: Operating System :: POSIX :: Linux
Classifier: Intended Audience :: Science/Research
Classifier: Topic :: Multimedia :: Sound/Audio :: Speech
